openi/__init__.py
openi/_login.py
openi/apis.py
openi/cli.py
openi/login.py
openi/context/__init__.py
openi/context/context.py
openi/context/download.py
openi/context/env_check.py
openi/context/helper.py
openi/context/upload.py
openi/dataset/__init__.py
openi/dataset/dataset.py
openi/dataset/download.py
openi/dataset/upload.py
openi/model/__init__.py
openi/model/download.py
openi/model/upload.py
openi/services/__init__.py
openi/services/dataset_struct.py
openi/services/file_download.py
openi/services/file_progress_bar.py
openi/services/file_upload.py
openi/services/model_struct.py
openi/services/repo_struct.py
openi/utils/__init__.py
openi/utils/constants.py
openi/utils/logger.py
openi_beta-2.2.8.dist-info/METADATA
openi_beta-2.2.8.dist-info/WHEEL
openi_beta-2.2.8.dist-info/top_level.txt
openi_beta-2.2.8.dist-info/RECORD
